myclusterui
