Metadata-Version: 1.1
Name: MyClusterUI
Version: 0.1.3
Summary: UI for MyCluster Application
Home-page: https://github.com/zenotech/MyClusterUI
Author: Zenotech
Author-email: admin@zenotech.com
License: BSD
Platform: UNKNOWN
Classifier: Development Status :: 4 - Beta
Classifier: Intended Audience :: Developers
Classifier: License :: OSI Approved :: BSD License
Classifier: Topic :: System :: Logging
Classifier: Programming Language :: Python
Classifier: Programming Language :: Python :: 2
Classifier: Programming Language :: Python :: 2.7
Classifier: Operating System :: POSIX :: Linux
